{
    "id": 5,
    "name": "ACNet2 2",
    "experiments": [
        {
            "id": 13,
            "aspectConfigurations": [
                {
                    "id": 13,
                    "instance": "acnet2",
                    "watchedVariables": [
                        "acnet2.pyramidals_48[0].soma_0.v",
                        "acnet2.pyramidals_48[1].soma_0.v"
                    ],
                    "modelParameters": [],
                    "simulatorConfiguration": {
                        "id": 13,
                        "simulatorId": "neuronSimulator",
                        "conversionServiceId": "lemsConversion",
                        "timestep": 5.0E-5,
                        "length": 0.15,
                        "parameters": {
                            "target": "network_ACnet2"
                        }
                    }
                }
            ],
            "name": "Experiment ready to execute",
            "description": "",
            "creationDate": 1473267723,
            "lastModified": 1495104391,
            "status": "COMPLETED",
            "simulationResults": [
                {
                    "id": 293,
                    "simulatedInstance": "acnet2",
                    "result": {
                        "id": 397,
                        "url": "/results_18052017_114646.h5",
                        "type": "RECORDING"
                    },
                    "format": "GEPPETTO_RECORDING"
                },
                {
                    "id": 294,
                    "simulatedInstance": "acnet2",
                    "result": {
                        "id": 398,
                        "url": "/rawRecording.zip",
                        "type": "RECORDING"
                    },
                    "format": "RAW"
                }
            ],
            "startDate": 1495104391,
            "endDate": 1495104409,
            "isPublic": false,
            "view": {
                "id": 118,
                "viewStates": {
                    "views": {
                        "Plot1": {
                            "widgetType": 0,
                            "isWidget": true,
                            "transparentBackground": false,
                            "name": "Recorded variables: v",
                            "size": {
                                "height": 382.8,
                                "width": 524.8
                            },
                            "position": {
                                "left": 131,
                                "top": 59
                            },
                            "dataType": "object",
                            "data": [
                                "acnet2.pyramidals_48[0].soma_0.v",
                                "acnet2.pyramidals_48[1].soma_0.v"
                            ]
                        },
                        "Canvas1": {
                            "widgetType": "CANVAS",
                            "isWidget": false,
                            "dataType": "instances",
                            "data": [
                                "acnet2"
                            ],
                            "componentSpecific": {
                                "cameraPosition": {
                                    "x": -59.25,
                                    "y": 648.032,
                                    "z": 67.759
                                },
                                "cameraRotation": {
                                    "rx": -1.731,
                                    "ry": -0.557,
                                    "rz": -1.895,
                                    "radius": 194.232
                                },
                                "colorMap": {
                                    "acnet2": "0x991140"
                                },
                                "colorFunctionMap": {},
                                "opacityMap": {},
                                "geometryTypeMap": {},
                                "backgroundColor": "0x101010"
                            }
                        },
                        "Tutorial1": {
                            "widgetType": "TUTORIAL",
                            "isWidget": true,
                            "dataType": "array",
                            "data": [
                                "https://raw.githubusercontent.com/tarelli/tutorials/master/1_hh_exercises/hh_exercises.json",
                                "https://raw.githubusercontent.com/tarelli/tutorials/master/1_hh_practical/hh_practical.json",
                                "https://raw.githubusercontent.com/tarelli/tutorials/master/1_hh_intro/hh_intro.json",
                                "https://raw.githubusercontent.com/tarelli/tutorials/master/1_hh_neuroml/hh_neuroml.json"
                            ],
                            "componentSpecific": {
                                "activeTutorial": "Open Source Brain Tutorial",
                                "currentStep": 0
                            },
                            "size": {
                                "height": 300,
                                "width": 350
                            },
                            "position": {
                                "left": "50%",
                                "top": "50%"
                            }
                        }
                    }
                }
            }
        }
    ],
    "activeExperimentId": 13,
    "geppettoModel": {
        "id": 13,
        "url": "/GeppettoModel.xmi",
        "type": "GEPPETTO_PROJECT"
    },
    "isPublic": false,
    "view": {
        "id": 119,
        "viewStates": {
            "views": {
                "Canvas1": {}
            }
        }
    }
}